Workbook

Sheet Primer año
A1: Control de Ingresos Egresos - Primer año
B3: Ingresos: | C3: =SUM($C$6:$C$9) -> 2750 | F3: Egresos: | G3: =SUM($G$6:$G$10) -> 800
A5: Mes | B5: Descripción | C5: Monto | E5: Mes | F5: Descripción | G5: Monto
A6: Enero | B6: Sueldo | C6: 1000 | E6: Enero | F6: Pago Hipoteca | G6: 200
B7: Pago Intereses | C7: 250 | F7: Escuelas | G7: 150
A8: Febrero | B8: Sueldo | C8: 1000 | F8: Diversion | G8: 100
B9: Intereses Renta | C9: 500 | E9: Febrero | F9: Ropa | G9: 200
F10: Escuelas | G10: 150

Sheet Reporte Mensual Primer año
A1: Reporte Mensual Primer año
B3: Enero | C3: Febrero | D3: Marzo | E3: Abril | F3: Mayo | G3: Etc. | H3: Totales
A4: Ingresos | B4: =SUM('Primer año'!$C$6:$C$7) -> 1250 | C4: =SUM('Primer año'!$C$8:$C$9) -> 1500 | D4: =SUM(D2:D3) -> 0 | E4: =SUM(E2:E3) -> 0 | F4: =SUM(F2:F3) -> 0 | G4: =SUM(G2:G3) -> 0 | H4: =SUM(B4:G4) -> 2750
A5: Egresos | B5: =SUM('Primer año'!$G$6:$G$8) -> 450 | C5: =SUM('Primer año'!$G$9:$G$10) -> 350 | D5: =SUM(D3:D4) -> 0 | E5: =SUM(E3:E4) -> 0 | F5: =SUM(F3:F4) -> 0 | G5: =SUM(G3:G4) -> 0 | H5: =SUM(B5:G5) -> 800
A6: Saldo Total | B6: =SUM(B4-B5) -> 800 | C6: =SUM(C4-C5) -> 1150 | D6: =SUM(D4-D5) -> 0 | E6: =SUM(E4-E5) -> 0 | F6: =SUM(F4-F5) -> 0 | G6: =SUM(G4-G5) -> 0 | H6: =SUM(H4-H5) -> 1950

Sheet Segundo año
A1: Control de Ingresos Egresos - Segundo año
B3: Ingresos: | C3: =SUM($C$6:$C$9) -> 2800 | F3: Egresos: | G3: =SUM($G$6:$G$10) -> 1000
A5: Mes | B5: Descripción | C5: Monto | E5: Mes | F5: Descripción | G5: Monto
A6: Enero | B6: Sueldo | C6: 1200 | E6: Enero | F6: Despensa | G6: 300
B7: Plazo Fijo | C7: 100 | F7: Seguros | G7: 200
A8: Febrero | B8: Sueldo | C8: 1200 | F8: Diversion | G8: 100
B9: Venta Celular | C9: 300 | E9: Febrero | F9: Gimnasio | G9: 100
F10: Escuelas | G10: 300

Sheet Reporte Mensual Segundo año
A1: Reporte Mensual Segundo año
B3: Enero | C3: Febrero | D3: Marzo | E3: Abril | F3: Mayo | G3: Etc. | H3: Totales
A4: Ingresos | B4: =SUM('Segundo año'!$C$6:$C$7) -> 1300 | C4: =SUM('Segundo año'!$C$8:$C$9) -> 1500 | D4: 0 | E4: 0 | F4: 0 | G4: 0 | H4: =SUM(B4:G4) -> 2800
A5: Egresos | B5: =SUM('Segundo año'!$G$6:$G$8) -> 600 | C5: =SUM('Segundo año'!$G$9:$G$10) -> 400 | D5: 0 | E5: 0 | F5: 0 | G5: 0 | H5: =SUM(B5:G5) -> 1000
A6: Saldo Total | B6: =SUM(B4-B5) -> 700 | C6: =SUM(C4-C5) -> 1100 | D6: 0 | E6: 0 | F6: 0 | G6: 0 | H6: =SUM(H4-H5) -> 1800

Sheet Totales
A1: Control de Ingresos Egresos Totales
A3: Ingresos Totales: | B3: =SUM('Reporte Mensual Primer año'!$H$4+'Reporte Mensual Segundo año'!$H$4) -> 5550 | D3: Egresos Totales: | E3: =SUM('Reporte Mensual Primer año'!$H$5+'Reporte Mensual Segundo año'!$H$5) -> 1800 | G3: Saldo Total: | H3: =SUM('Reporte Mensual Primer año'!$H$6+'Reporte Mensual Segundo año'!$H$6) -> 3750
